setup.py
sharkpyro/__init__.py
sharkpyro/client.py
sharkpyro/dispatcher.py
sharkpyro/emoji.py
sharkpyro/file_id.py
sharkpyro/filters.py
sharkpyro/mime_types.py
sharkpyro/scaffold.py
sharkpyro/sync.py
sharkpyro/syncer.py
sharkpyro/utils.py
sharkpyro.egg-info/PKG-INFO
sharkpyro.egg-info/SOURCES.txt
sharkpyro.egg-info/dependency_links.txt
sharkpyro.egg-info/requires.txt
sharkpyro.egg-info/top_level.txt
sharkpyro/connection/__init__.py
sharkpyro/connection/connection.py
sharkpyro/connection/transport/__init__.py
sharkpyro/connection/transport/tcp/__init__.py
sharkpyro/connection/transport/tcp/tcp.py
sharkpyro/connection/transport/tcp/tcp_abridged.py
sharkpyro/connection/transport/tcp/tcp_abridged_o.py
sharkpyro/connection/transport/tcp/tcp_full.py
sharkpyro/connection/transport/tcp/tcp_intermediate.py
sharkpyro/connection/transport/tcp/tcp_intermediate_o.py
sharkpyro/crypto/__init__.py
sharkpyro/crypto/aes.py
sharkpyro/crypto/mtproto.py
sharkpyro/crypto/prime.py
sharkpyro/crypto/rsa.py
sharkpyro/errors/__init__.py
sharkpyro/errors/rpc_error.py
sharkpyro/errors/exceptions/__init__.py
sharkpyro/errors/exceptions/all.py
sharkpyro/errors/exceptions/bad_request_400.py
sharkpyro/errors/exceptions/flood_420.py
sharkpyro/errors/exceptions/forbidden_403.py
sharkpyro/errors/exceptions/internal_server_error_500.py
sharkpyro/errors/exceptions/not_acceptable_406.py
sharkpyro/errors/exceptions/see_other_303.py
sharkpyro/errors/exceptions/service_unavailable_503.py
sharkpyro/errors/exceptions/unauthorized_401.py
sharkpyro/handlers/__init__.py
sharkpyro/handlers/callback_query_handler.py
sharkpyro/handlers/chat_join_request_handler.py
sharkpyro/handlers/chat_member_updated_handler.py
sharkpyro/handlers/chosen_inline_result_handler.py
sharkpyro/handlers/deleted_messages_handler.py
sharkpyro/handlers/disconnect_handler.py
sharkpyro/handlers/handler.py
sharkpyro/handlers/inline_query_handler.py
sharkpyro/handlers/message_handler.py
sharkpyro/handlers/poll_handler.py
sharkpyro/handlers/raw_update_handler.py
sharkpyro/handlers/user_status_handler.py
sharkpyro/methods/__init__.py
sharkpyro/methods/advanced/__init__.py
