Metadata-Version: 2.1
Name: sharkpyro
Version: 1.4.4
Summary: Pyrogram fork for SharkUserBot
Author: Dan
Author-email: dan@pyrogram.org
